urluckynum/app/__init__.py
urluckynum/app/argparser.py
urluckynum/app/db.py
urluckynum/app/lucky.py
urluckynum/app/queries.py
urluckynum-9.35.dist-info/METADATA
urluckynum-9.35.dist-info/WHEEL
urluckynum-9.35.dist-info/top_level.txt
urluckynum-9.35.dist-info/RECORD
