Metadata-Version: 2.1
Name: urluckynum
Version: 9.35
Summary: My Application with a DB
Author: LuckyWave Group
Requires-Dist: prospector
Requires-Dist: bandit
Requires-Dist: pytest
Requires-Dist: mysql-connector-python
Requires-Dist: setuptools
Requires-Dist: wheel
Requires-Dist: twine
Requires-Dist: pdoc
